{"schemaVersion":1,"file":"1 Algebraic functions/1.2 Trinomial products/1.2.2 Quartic/1.2.2.2 (d x)^m (a+b x^2+c x^4)^p.m","rules":[
{"index":1,"lhs":["Multiply",["Power",["Multiply",["BlankOptional","d"],["Blank","x"]],["BlankOptional","m"]],["Power",["Add",["Multiply",["BlankOptional","b"],["Power",["Blank","x"],2]],["Multiply",["BlankOptional","c"],["Power",["Blank","x"],4]]],["Blank","p"]]],"variable":"x","rhs":["Multiply",["Divide",1,["Power","d",["Multiply",2,"p"]]],["Int",["Multiply",["Power",["Multiply","d","x"],["Add","m",["Multiply",2,"p"]]],["Power",["Add","b",["Multiply","c",["Power","x",2]]],"p"]],"x"]],"condition":["And",["FreeQ",["List","b","c","d","m"],"x"],["IntegerQ","p"]],"bindings":[],"scoped":null,"innerCondition":null,"source":"Int[(d_.*x_)^m_.*(b_.*x_^2+c_.*x_^4)^p_,x_Symbol] :=\r\n  1/d^(2*p) \\[Star] Int[(d*x)^(m+2*p)*(b+c*x^2)^p,x] /;\r\nFreeQ[{b,c,d,m},x] && IntegerQ[p]"},
{"index":2,"lhs":["Multiply",["Power",["Multiply",["BlankOptional","d"],["Blank","x"]],["Blank","m"]],["Power",["Add",["Multiply",["BlankOptional","b"],["Power",["Blank","x"],2]],["Multiply",["BlankOptional","c"],["Power",["Blank","x"],4]]],["Blank","p"]]],"variable":"x","rhs":["Divide",["Multiply",["Power","d",3],["Power",["Multiply","d","x"],["Subtract","m",3]],["Power",["Add",["Multiply","b",["Power","x",2]],["Multiply","c",["Power","x",4]]],["Add","p",1]]],["Multiply",2,"c",["Add","p",1]]],"condition":["And",["FreeQ",["List","b","c","d","m","p"],"x"],["Not",["IntegerQ","p"]],["EqQ",["Subtract",["Add","m",["Multiply",2,"p"]],1],0]],"bindings":[],"scoped":null,"innerCondition":null,"source":"Int[(d_.*x_)^m_*(b_.*x_^2+c_.*x_^4)^p_,x_Symbol] :=\r\n  d^3*(d*x)^(m-3)*(b*x^2+c*x^4)^(p+1)/(2*c*(p+1)) /;\r\nFreeQ[{b,c,d,m,p},x] && Not[IntegerQ[p]] && EqQ[m+2*p-1,0]"},
{"index":3,"lhs":["Multiply",["Power",["Multiply",["BlankOptional","d"],["Blank","x"]],["Blank","m"]],["Power",["Add",["Multiply",["BlankOptional","b"],["Power",["Blank","x"],2]],["Multiply",["BlankOptional","c"],["Power",["Blank","x"],4]]],["Blank","p"]]],"variable":"x","rhs":["Subtract",["Divide",["Multiply",["Power","d",3],["Power",["Multiply","d","x"],["Subtract","m",3]],["Power",["Add",["Multiply","b",["Power","x",2]],["Multiply","c",["Power","x",4]]],["Add","p",1]]],["Multiply","c",["Add","m",["Multiply",4,"p"],1]]],["Multiply",["Divide",["Multiply","b",["Power","d",2],["Subtract",["Add","m",["Multiply",2,"p"]],1]],["Multiply","c",["Add","m",["Multiply",4,"p"],1]]],["Int",["Multiply",["Power",["Multiply","d","x"],["Subtract","m",2]],["Power",["Add",["Multiply","b",["Power","x",2]],["Multiply","c",["Power","x",4]]],"p"]],"x"]]],"condition":["And",["FreeQ",["List","b","c","d","m","p"],"x"],["Not",["IntegerQ","p"]],["IGtQ",["Simplify",["Divide",["Subtract",["Add","m",["Multiply",2,"p"]],1],2]],0],["NeQ",["Add","m",["Multiply",4,"p"],1],0]],"bindings":[],"scoped":null,"innerCondition":null,"source":"Int[(d_.*x_)^m_*(b_.*x_^2+c_.*x_^4)^p_,x_Symbol] :=\r\n  d^3*(d*x)^(m-3)*(b*x^2+c*x^4)^(p+1)/(c*(m+4*p+1)) - \r\n  b*d^2*(m+2*p-1)/(c*(m+4*p+1)) \\[Star] Int[(d*x)^(m-2)*(b*x^2+c*x^4)^p,x] /;\r\nFreeQ[{b,c,d,m,p},x] && Not[IntegerQ[p]] && IGtQ[Simplify[(m+2*p-1)/2],0] && NeQ[m+4*p+1,0]"},
{"index":4,"lhs":["Multiply",["Power",["Multiply",["BlankOptional","d"],["Blank","x"]],["Blank","m"]],["Power",["Add",["Multiply",["BlankOptional","b"],["Power",["Blank","x"],2]],["Multiply",["BlankOptional","c"],["Power",["Blank","x"],4]]],["Blank","p"]]],"variable":"x","rhs":["Negate",["Divide",["Multiply","d",["Power",["Multiply","d","x"],["Subtract","m",1]],["Power",["Add",["Multiply","b",["Power","x",2]],["Multiply","c",["Power","x",4]]],["Add","p",1]]],["Multiply",2,"b",["Add","p",1]]]],"condition":["And",["FreeQ",["List","b","c","d","m","p"],"x"],["Not",["IntegerQ","p"]],["EqQ",["Add","m",["Multiply",4,"p"],3],0]],"bindings":[],"scoped":null,"innerCondition":null,"source":"Int[(d_.*x_)^m_*(b_.*x_^2+c_.*x_^4)^p_,x_Symbol] :=\r\n  -d*(d*x)^(m-1)*(b*x^2+c*x^4)^(p+1)/(2*b*(p+1)) /;\r\nFreeQ[{b,c,d,m,p},x] && Not[IntegerQ[p]] && EqQ[m+4*p+3,0]"},
{"index":5,"lhs":["Multiply",["Power",["Multiply",["BlankOptional","d"],["Blank","x"]],["Blank","m"]],["Power",["Add",["Multiply",["BlankOptional","b"],["Power",["Blank","x"],2]],["Multiply",["BlankOptional","c"],["Power",["Blank","x"],4]]],["Blank","p"]]],"variable":"x","rhs":["Subtract",["Divide",["Multiply","d",["Power",["Multiply","d","x"],["Subtract","m",1]],["Power",["Add",["Multiply","b",["Power","x",2]],["Multiply","c",["Power","x",4]]],["Add","p",1]]],["Multiply","b",["Add","m",["Multiply",2,"p"],1]]],["Multiply",["Divide",["Multiply","c",["Add","m",["Multiply",4,"p"],3]],["Multiply","b",["Power","d",2],["Add","m",["Multiply",2,"p"],1]]],["Int",["Multiply",["Power",["Multiply","d","x"],["Add","m",2]],["Power",["Add",["Multiply","b",["Power","x",2]],["Multiply","c",["Power","x",4]]],"p"]],"x"]]],"condition":["And",["FreeQ",["List","b","c","d","m","p"],"x"],["Not",["IntegerQ","p"]],["ILtQ",["Simplify",["Divide",["Add","m",["Multiply",4,"p"],3],2]],0],["NeQ",["Add","m",["Multiply",2,"p"],1],0]],"bindings":[],"scoped":null,"innerCondition":null,"source":"Int[(d_.*x_)^m_*(b_.*x_^2+c_.*x_^4)^p_,x_Symbol] :=\r\n  d*(d*x)^(m-1)*(b*x^2+c*x^4)^(p+1)/(b*(m+2*p+1)) - \r\n  c*(m+4*p+3)/(b*d^2*(m+2*p+1)) \\[Star] Int[(d*x)^(m+2)*(b*x^2+c*x^4)^p,x] /;\r\nFreeQ[{b,c,d,m,p},x] && Not[IntegerQ[p]] && ILtQ[Simplify[(m+4*p+3)/2],0] && NeQ[m+2*p+1,0]"},
{"index":6,"lhs":["Multiply",["Power",["Blank","x"],["BlankOptional","m"]],["Power",["Add",["Multiply",["BlankOptional","b"],["Power",["Blank","x"],2]],["Multiply",["BlankOptional","c"],["Power",["Blank","x"],4]]],["Blank","p"]]],"variable":"x","rhs":["Multiply",["Rational",1,2],["Subst",["Int",["Multiply",["Power","x",["Divide",["Subtract","m",1],2]],["Power",["Add",["Multiply","b","x"],["Multiply","c",["Power","x",2]]],"p"]],"x"],"x",["Power","x",2]]],"condition":["And",["FreeQ",["List","b","c","m","p"],"x"],["Not",["IntegerQ","p"]],["IntegerQ",["Divide",["Subtract","m",1],2]]],"bindings":[],"scoped":null,"innerCondition":null,"source":"Int[x_^m_.*(b_.*x_^2+c_.*x_^4)^p_,x_Symbol] :=\r\n  1/2 \\[Star] Subst[Int[x^((m-1)/2)*(b*x+c*x^2)^p,x],x,x^2] /;\r\nFreeQ[{b,c,m,p},x] && Not[IntegerQ[p]] && IntegerQ[(m-1)/2]"},
{"index":7,"lhs":["Multiply",["Power",["Multiply",["BlankOptional","d"],["Blank","x"]],["Blank","m"]],["Power",["Add",["Multiply",["BlankOptional","b"],["Power",["Blank","x"],2]],["Multiply",["BlankOptional","c"],["Power",["Blank","x"],4]]],["Blank","p"]]],"variable":"x","rhs":["Subtract",["Divide",["Multiply",["Power",["Multiply","d","x"],["Add","m",1]],["Power",["Add",["Multiply","b",["Power","x",2]],["Multiply","c",["Power","x",4]]],"p"]],["Multiply","d",["Add","m",["Multiply",2,"p"],1]]],["Multiply",["Divide",["Multiply",2,"c","p"],["Multiply",["Power","d",4],["Add","m",["Multiply",2,"p"],1]]],["Int",["Multiply",["Power",["Multiply","d","x"],["Add","m",4]],["Power",["Add",["Multiply","b",["Power","x",2]],["Multiply","c",["Power","x",4]]],["Subtract","p",1]]],"x"]]],"condition":["And",["FreeQ",["List","b","c","d","m","p"],"x"],["Not",["IntegerQ","p"]],["GtQ","p",0],["LtQ",["Add","m",["Multiply",2,"p"],1],0]],"bindings":[],"scoped":null,"innerCondition":null,"source":"Int[(d_.*x_)^m_*(b_.*x_^2+c_.*x_^4)^p_,x_Symbol] :=\r\n  (d*x)^(m+1)*(b*x^2+c*x^4)^p/(d*(m+2*p+1)) - \r\n  2*c*p/(d^4*(m+2*p+1)) \\[Star] Int[(d*x)^(m+4)*(b*x^2+c*x^4)^(p-1),x] /;\r\nFreeQ[{b,c,d,m,p},x] && Not[IntegerQ[p]] && GtQ[p,0] && LtQ[m+2*p+1,0]"},
{"index":8,"lhs":["Multiply",["Power",["Multiply",["BlankOptional","d"],["Blank","x"]],["Blank","m"]],["Power",["Add",["Multiply",["BlankOptional","b"],["Power",["Blank","x"],2]],["Multiply",["BlankOptional","c"],["Power",["Blank","x"],4]]],["Blank","p"]]],"variable":"x","rhs":["Add",["Divide",["Multiply",["Power",["Multiply","d","x"],["Add","m",1]],["Power",["Add",["Multiply","b",["Power","x",2]],["Multiply","c",["Power","x",4]]],"p"]],["Multiply","d",["Add","m",["Multiply",4,"p"],1]]],["Multiply",["Divide",["Multiply",2,"b","p"],["Multiply",["Power","d",2],["Add","m",["Multiply",4,"p"],1]]],["Int",["Multiply",["Power",["Multiply","d","x"],["Add","m",2]],["Power",["Add",["Multiply","b",["Power","x",2]],["Multiply","c",["Power","x",4]]],["Subtract","p",1]]],"x"]]],"condition":["And",["FreeQ",["List","b","c","d","m","p"],"x"],["Not",["IntegerQ","p"]],["GtQ","p",0],["NeQ",["Add","m",["Multiply",4,"p"],1],0]],"bindings":[],"scoped":null,"innerCondition":null,"source":"Int[(d_.*x_)^m_*(b_.*x_^2+c_.*x_^4)^p_,x_Symbol] :=\r\n  (d*x)^(m+1)*(b*x^2+c*x^4)^p/(d*(m+4*p+1)) + \r\n  2*b*p/(d^2*(m+4*p+1)) \\[Star] Int[(d*x)^(m+2)*(b*x^2+c*x^4)^(p-1),x] /;\r\nFreeQ[{b,c,d,m,p},x] && Not[IntegerQ[p]] && GtQ[p,0] && NeQ[m+4*p+1,0]"},
{"index":9,"lhs":["Multiply",["Power",["Multiply",["BlankOptional","d"],["Blank","x"]],["Blank","m"]],["Power",["Add",["Multiply",["BlankOptional","b"],["Power",["Blank","x"],2]],["Multiply",["BlankOptional","c"],["Power",["Blank","x"],4]]],["Blank","p"]]],"variable":"x","rhs":["Subtract",["Divide",["Multiply",["Power","d",3],["Power",["Multiply","d","x"],["Subtract","m",3]],["Power",["Add",["Multiply","b",["Power","x",2]],["Multiply","c",["Power","x",4]]],["Add","p",1]]],["Multiply",2,"c",["Add","p",1]]],["Multiply",["Divide",["Multiply",["Power","d",4],["Subtract",["Add","m",["Multiply",2,"p"]],1]],["Multiply",2,"c",["Add","p",1]]],["Int",["Multiply",["Power",["Multiply","d","x"],["Subtract","m",4]],["Power",["Add",["Multiply","b",["Power","x",2]],["Multiply","c",["Power","x",4]]],["Add","p",1]]],"x"]]],"condition":["And",["FreeQ",["List","b","c","d","m","p"],"x"],["Not",["IntegerQ","p"]],["LtQ","p",-1],["GtQ",["Add","m",["Multiply",2,"p"],1],2]],"bindings":[],"scoped":null,"innerCondition":null,"source":"Int[(d_.*x_)^m_*(b_.*x_^2+c_.*x_^4)^p_,x_Symbol] :=\r\n  d^3*(d*x)^(m-3)*(b*x^2+c*x^4)^(p+1)/(2*c*(p+1)) - \r\n  d^4*(m+2*p-1)/(2*c*(p+1)) \\[Star] Int[(d*x)^(m-4)*(b*x^2+c*x^4)^(p+1),x] /;\r\nFreeQ[{b,c,d,m,p},x] && Not[IntegerQ[p]] && LtQ[p,-1] && GtQ[m+2*p+1,2]"},
{"index":10,"lhs":["Multiply",["Power",["Multiply",["BlankOptional","d"],["Blank","x"]],["Blank","m"]],["Power",["Add",["Multiply",["BlankOptional","b"],["Power",["Blank","x"],2]],["Multiply",["BlankOptional","c"],["Power",["Blank","x"],4]]],["Blank","p"]]],"variable":"x","rhs":["Add",["Negate",["Divide",["Multiply","d",["Power",["Multiply","d","x"],["Subtract","m",1]],["Power",["Add",["Multiply","b",["Power","x",2]],["Multiply","c",["Power","x",4]]],["Add","p",1]]],["Multiply",2,"b",["Add","p",1]]]],["Multiply",["Divide",["Multiply",["Power","d",2],["Add","m",["Multiply",4,"p"],3]],["Multiply",2,"b",["Add","p",1]]],["Int",["Multiply",["Power",["Multiply","d","x"],["Subtract","m",2]],["Power",["Add",["Multiply","b",["Power","x",2]],["Multiply","c",["Power","x",4]]],["Add","p",1]]],"x"]]],"condition":["And",["FreeQ",["List","b","c","d","m","p"],"x"],["Not",["IntegerQ","p"]],["LtQ","p",-1]],"bindings":[],"scoped":null,"innerCondition":null,"source":"Int[(d_.*x_)^m_*(b_.*x_^2+c_.*x_^4)^p_,x_Symbol] :=\r\n  -d*(d*x)^(m-1)*(b*x^2+c*x^4)^(p+1)/(2*b*(p+1)) + \r\n  d^2*(m+4*p+3)/(2*b*(p+1)) \\[Star] Int[(d*x)^(m-2)*(b*x^2+c*x^4)^(p+1),x] /;\r\nFreeQ[{b,c,d,m,p},x] && Not[IntegerQ[p]] && LtQ[p,-1]"},
{"index":11,"lhs":["Multiply",["Power",["Multiply",["BlankOptional","d"],["Blank","x"]],["Blank","m"]],["Power",["Add",["Multiply",["BlankOptional","b"],["Power",["Blank","x"],2]],["Multiply",["BlankOptional","c"],["Power",["Blank","x"],4]]],["Blank","p"]]],"variable":"x","rhs":["Subtract",["Divide",["Multiply",["Power","d",3],["Power",["Multiply","d","x"],["Subtract","m",3]],["Power",["Add",["Multiply","b",["Power","x",2]],["Multiply","c",["Power","x",4]]],["Add","p",1]]],["Multiply","c",["Add","m",["Multiply",4,"p"],1]]],["Multiply",["Divide",["Multiply","b",["Power","d",2],["Subtract",["Add","m",["Multiply",2,"p"]],1]],["Multiply","c",["Add","m",["Multiply",4,"p"],1]]],["Int",["Multiply",["Power",["Multiply","d","x"],["Subtract","m",2]],["Power",["Add",["Multiply","b",["Power","x",2]],["Multiply","c",["Power","x",4]]],"p"]],"x"]]],"condition":["And",["FreeQ",["List","b","c","d","m","p"],"x"],["Not",["IntegerQ","p"]],["GtQ",["Subtract",["Add","m",["Multiply",2,"p"]],1],0],["NeQ",["Add","m",["Multiply",4,"p"],1],0]],"bindings":[],"scoped":null,"innerCondition":null,"source":"Int[(d_.*x_)^m_*(b_.*x_^2+c_.*x_^4)^p_,x_Symbol] :=\r\n  d^3*(d*x)^(m-3)*(b*x^2+c*x^4)^(p+1)/(c*(m+4*p+1)) - \r\n  b*d^2*(m+2*p-1)/(c*(m+4*p+1)) \\[Star] Int[(d*x)^(m-2)*(b*x^2+c*x^4)^p,x] /;\r\nFreeQ[{b,c,d,m,p},x] && Not[IntegerQ[p]] && GtQ[m+2*p-1,0] && NeQ[m+4*p+1,0]"},
{"index":12,"lhs":["Multiply",["Power",["Multiply",["BlankOptional","d"],["Blank","x"]],["Blank","m"]],["Power",["Add",["Multiply",["BlankOptional","b"],["Power",["Blank","x"],2]],["Multiply",["BlankOptional","c"],["Power",["Blank","x"],4]]],["Blank","p"]]],"variable":"x","rhs":["Subtract",["Divide",["Multiply","d",["Power",["Multiply","d","x"],["Subtract","m",1]],["Power",["Add",["Multiply","b",["Power","x",2]],["Multiply","c",["Power","x",4]]],["Add","p",1]]],["Multiply","b",["Add","m",["Multiply",2,"p"],1]]],["Multiply",["Divide",["Multiply","c",["Add","m",["Multiply",4,"p"],3]],["Multiply","b",["Power","d",2],["Add","m",["Multiply",2,"p"],1]]],["Int",["Multiply",["Power",["Multiply","d","x"],["Add","m",2]],["Power",["Add",["Multiply","b",["Power","x",2]],["Multiply","c",["Power","x",4]]],"p"]],"x"]]],"condition":["And",["FreeQ",["List","b","c","d","m","p"],"x"],["Not",["IntegerQ","p"]],["LtQ",["Add","m",["Multiply",2,"p"],1],0]],"bindings":[],"scoped":null,"innerCondition":null,"source":"Int[(d_.*x_)^m_*(b_.*x_^2+c_.*x_^4)^p_,x_Symbol] :=\r\n  d*(d*x)^(m-1)*(b*x^2+c*x^4)^(p+1)/(b*(m+2*p+1)) - \r\n  c*(m+4*p+3)/(b*d^2*(m+2*p+1)) \\[Star] Int[(d*x)^(m+2)*(b*x^2+c*x^4)^p,x] /;\r\nFreeQ[{b,c,d,m,p},x] && Not[IntegerQ[p]] && LtQ[m+2*p+1,0]"},
{"index":13,"lhs":["Multiply",["Power",["Multiply",["BlankOptional","d"],["Blank","x"]],["Blank","m"]],["Power",["Add",["Multiply",["BlankOptional","b"],["Power",["Blank","x"],2]],["Multiply",["BlankOptional","c"],["Power",["Blank","x"],4]]],["Blank","p"]]],"variable":"x","rhs":["Multiply",["Divide",["Power",["Add",["Multiply","b",["Power","x",2]],["Multiply","c",["Power","x",4]]],"p"],["Multiply",["Power",["Multiply","d","x"],["Multiply",2,"p"]],["Power",["Add","b",["Multiply","c",["Power","x",2]]],"p"]]],["Int",["Multiply",["Power",["Multiply","d","x"],["Add","m",["Multiply",2,"p"]]],["Power",["Add","b",["Multiply","c",["Power","x",2]]],"p"]],"x"]],"condition":["And",["FreeQ",["List","b","c","d","m","p"],"x"],["Not",["IntegerQ","p"]]],"bindings":[],"scoped":null,"innerCondition":null,"source":"Int[(d_.*x_)^m_*(b_.*x_^2+c_.*x_^4)^p_,x_Symbol] :=\r\n  (b*x^2+c*x^4)^p/((d*x)^(2*p)*(b+c*x^2)^p) \\[Star] Int[(d*x)^(m+2*p)*(b+c*x^2)^p,x] /;\r\nFreeQ[{b,c,d,m,p},x] && Not[IntegerQ[p]]"},
{"index":14,"lhs":["Multiply",["Blank","x"],["Power",["Add",["Blank","a"],["Multiply",["BlankOptional","b"],["Power",["Blank","x"],2]],["Multiply",["BlankOptional","c"],["Power",["Blank","x"],4]]],["Blank","p"]]],"variable":"x","rhs":["Multiply",["Rational",1,2],["Subst",["Int",["Power",["Add","a",["Multiply","b","x"],["Multiply","c",["Power","x",2]]],"p"],"x"],"x",["Power","x",2]]],"condition":["FreeQ",["List","a","b","c","p"],"x"],"bindings":[],"scoped":null,"innerCondition":null,"source":"Int[x_*(a_+b_.*x_^2+c_.*x_^4)^p_,x_Symbol] :=\r\n  1/2 \\[Star] Subst[Int[(a+b*x+c*x^2)^p,x],x,x^2] /;\r\nFreeQ[{a,b,c,p},x]"},
{"index":15,"lhs":["Multiply",["Power",["Multiply",["BlankOptional","d"],["Blank","x"]],["Blank","m"]],["Power",["Add",["Blank","a"],["Multiply",["BlankOptional","b"],["Power",["Blank","x"],2]],["Multiply",["BlankOptional","c"],["Power",["Blank","x"],4]]],["BlankOptional","p"]]],"variable":"x","rhs":["Int",["ExpandIntegrand",["Multiply",["Power",["Multiply","d","x"],"m"],["Power",["Add","a",["Multiply","b",["Power","x",2]],["Multiply","c",["Power","x",4]]],"p"]],"x"],"x"],"condition":["And",["FreeQ",["List","a","b","c","d","m"],"x"],["IGtQ","p",0],["Or",["EqQ","p",1],["Not",["IntegerQ",["Divide",["Add","m",1],2]]]]],"bindings":[],"scoped":null,"innerCondition":null,"source":"Int[(d_.*x_)^m_*(a_+b_.*x_^2+c_.*x_^4)^p_.,x_Symbol] :=\r\n  Int[ExpandIntegrand[(d*x)^m*(a+b*x^2+c*x^4)^p,x],x] /;\r\nFreeQ[{a,b,c,d,m},x] && IGtQ[p,0] && (EqQ[p,1] || Not[IntegerQ[(m+1)/2]])"},
{"index":16,"lhs":["Multiply",["Power",["Blank","x"],["Blank","m"]],["Power",["Add",["Blank","a"],["Multiply",["BlankOptional","b"],["Power",["Blank","x"],2]],["Multiply",["BlankOptional","c"],["Power",["Blank","x"],4]]],["BlankOptional","p"]]],"variable":"x","rhs":["Multiply",["Rational",1,2],["Subst",["Int",["Multiply",["Power","x",["Divide",["Subtract","m",1],2]],["Power",["Add","a",["Multiply","b","x"],["Multiply","c",["Power","x",2]]],"p"]],"x"],"x",["Power","x",2]]],"condition":["And",["FreeQ",["List","a","b","c","p"],"x"],["IntegerQ",["Divide",["Subtract","m",1],2]]],"bindings":[],"scoped":null,"innerCondition":null,"source":"Int[x_^m_*(a_+b_.*x_^2+c_.*x_^4)^p_.,x_Symbol] :=\r\n  1/2 \\[Star] Subst[Int[x^((m-1)/2)*(a+b*x+c*x^2)^p,x],x,x^2] /;\r\nFreeQ[{a,b,c,p},x] && IntegerQ[(m-1)/2]"},
{"index":17,"lhs":["Multiply",["Power",["Multiply",["BlankOptional","d"],["Blank","x"]],["Blank","m"]],["Power",["Add",["Blank","a"],["Multiply",["BlankOptional","b"],["Power",["Blank","x"],2]],["Multiply",["BlankOptional","c"],["Power",["Blank","x"],4]]],["Blank","p"]]],"variable":"x","rhs":["Multiply",["Divide","k","d"],["Subst",["Int",["Multiply",["Power","x",["Subtract",["Multiply","k",["Add","m",1]],1]],["Power",["Add","a",["Divide",["Multiply","b",["Power","x",["Multiply",2,"k"]]],["Power","d",2]],["Divide",["Multiply","c",["Power","x",["Multiply",4,"k"]]],["Power","d",4]]],"p"]],"x"],"x",["Power",["Multiply","d","x"],["Divide",1,"k"]]]],"condition":["And",["FreeQ",["List","a","b","c","d","p"],"x"],["NeQ",["Subtract",["Power","b",2],["Multiply",4,"a","c"]],0],["FractionQ","m"],["IntegerQ","p"]],"bindings":[{"name":"k","value":["Denominator","m"]}],"scoped":"with","innerCondition":null,"source":"Int[(d_.*x_)^m_*(a_+b_.*x_^2+c_.*x_^4)^p_,x_Symbol] :=\r\n  With[{k=Denominator[m]},\r\n  k/d \\[Star] Subst[Int[x^(k*(m+1)-1)*(a+b*x^(2*k)/d^2+c*x^(4*k)/d^4)^p,x],x,(d*x)^(1/k)]] /;\r\nFreeQ[{a,b,c,d,p},x] && NeQ[b^2-4*a*c,0] && FractionQ[m] && IntegerQ[p]"},
{"index":18,"lhs":["Multiply",["Power",["Multiply",["BlankOptional","d"],["Blank","x"]],["Blank","m"]],["Power",["Add",["Blank","a"],["Multiply",["BlankOptional","b"],["Power",["Blank","x"],2]],["Multiply",["BlankOptional","c"],["Power",["Blank","x"],4]]],["Blank","p"]]],"variable":"x","rhs":["Subtract",["Divide",["Multiply","d",["Power",["Multiply","d","x"],["Subtract","m",1]],["Power",["Add","a",["Multiply","b",["Power","x",2]],["Multiply","c",["Power","x",4]]],"p"],["Add",["Multiply",2,"b","p"],["Multiply","c",["Subtract",["Add","m",["Multiply",4,"p"]],1],["Power","x",2]]]],["Multiply","c",["Add","m",["Multiply",4,"p"],1],["Subtract",["Add","m",["Multiply",4,"p"]],1]]],["Multiply",["Divide",["Multiply",2,"p",["Power","d",2]],["Multiply","c",["Add","m",["Multiply",4,"p"],1],["Subtract",["Add","m",["Multiply",4,"p"]],1]]],["Int",["Multiply",["Power",["Multiply","d","x"],["Subtract","m",2]],["Power",["Add","a",["Multiply","b",["Power","x",2]],["Multiply","c",["Power","x",4]]],["Subtract","p",1]],["Simp",["Subtract",["Multiply","a","b",["Subtract","m",1]],["Multiply",["Subtract",["Multiply",2,"a","c",["Subtract",["Add","m",["Multiply",4,"p"]],1]],["Multiply",["Power","b",2],["Subtract",["Add","m",["Multiply",2,"p"]],1]]],["Power","x",2]]],"x"]],"x"]]],"condition":["And",["FreeQ",["List","a","b","c","d"],"x"],["NeQ",["Subtract",["Power","b",2],["Multiply",4,"a","c"]],0],["GtQ","p",0],["GtQ","m",1],["IntegerQ",["Multiply",2,"p"]],["Or",["IntegerQ","p"],["IntegerQ","m"]]],"bindings":[],"scoped":null,"innerCondition":null,"source":"Int[(d_.*x_)^m_*(a_+b_.*x_^2+c_.*x_^4)^p_,x_Symbol] :=\r\n  d*(d*x)^(m-1)*(a+b*x^2+c*x^4)^p*(2*b*p+c*(m+4*p-1)*x^2)/(c*(m+4*p+1)*(m+4*p-1)) - \r\n  2*p*d^2/(c*(m+4*p+1)*(m+4*p-1)) \\[Star] \r\n    Int[(d*x)^(m-2)*(a+b*x^2+c*x^4)^(p-1)*Simp[a*b*(m-1)-(2*a*c*(m+4*p-1)-b^2*(m+2*p-1))*x^2,x],x] /;\r\nFreeQ[{a,b,c,d},x] && NeQ[b^2-4*a*c,0] && GtQ[p,0] && GtQ[m,1] && IntegerQ[2*p] && (IntegerQ[p] || IntegerQ[m])"},
{"index":19,"lhs":["Multiply",["Power",["Multiply",["BlankOptional","d"],["Blank","x"]],["Blank","m"]],["Power",["Add",["Blank","a"],["Multiply",["BlankOptional","b"],["Power",["Blank","x"],2]],["Multiply",["BlankOptional","c"],["Power",["Blank","x"],4]]],["Blank","p"]]],"variable":"x","rhs":["Subtract",["Divide",["Multiply",["Power",["Multiply","d","x"],["Add","m",1]],["Power",["Add","a",["Multiply","b",["Power","x",2]],["Multiply","c",["Power","x",4]]],"p"]],["Multiply","d",["Add","m",1]]],["Multiply",["Divide",["Multiply",2,"p"],["Multiply",["Power","d",2],["Add","m",1]]],["Int",["Multiply",["Power",["Multiply","d","x"],["Add","m",2]],["Add","b",["Multiply",2,"c",["Power","x",2]]],["Power",["Add","a",["Multiply","b",["Power","x",2]],["Multiply","c",["Power","x",4]]],["Subtract","p",1]]],"x"]]],"condition":["And",["FreeQ",["List","a","b","c","d"],"x"],["NeQ",["Subtract",["Power","b",2],["Multiply",4,"a","c"]],0],["GtQ","p",0],["LtQ","m",-1],["IntegerQ",["Multiply",2,"p"]],["Or",["IntegerQ","p"],["IntegerQ","m"]]],"bindings":[],"scoped":null,"innerCondition":null,"source":"Int[(d_.*x_)^m_*(a_+b_.*x_^2+c_.*x_^4)^p_,x_Symbol] :=\r\n  (d*x)^(m+1)*(a+b*x^2+c*x^4)^p/(d*(m+1)) - \r\n  2*p/(d^2*(m+1)) \\[Star] Int[(d*x)^(m+2)*(b+2*c*x^2)*(a+b*x^2+c*x^4)^(p-1),x] /;\r\nFreeQ[{a,b,c,d},x] && NeQ[b^2-4*a*c,0] && GtQ[p,0] && LtQ[m,-1] && IntegerQ[2*p] && (IntegerQ[p] || IntegerQ[m])"},
{"index":20,"lhs":["Multiply",["Power",["Multiply",["BlankOptional","d"],["Blank","x"]],["Blank","m"]],["Power",["Add",["Blank","a"],["Multiply",["BlankOptional","b"],["Power",["Blank","x"],2]],["Multiply",["BlankOptional","c"],["Power",["Blank","x"],4]]],["Blank","p"]]],"variable":"x","rhs":["Add",["Divide",["Multiply",["Power",["Multiply","d","x"],["Add","m",1]],["Power",["Add","a",["Multiply","b",["Power","x",2]],["Multiply","c",["Power","x",4]]],"p"]],["Multiply","d",["Add","m",["Multiply",4,"p"],1]]],["Multiply",["Divide",["Multiply",2,"p"],["Add","m",["Multiply",4,"p"],1]],["Int",["Multiply",["Power",["Multiply","d","x"],"m"],["Add",["Multiply",2,"a"],["Multiply","b",["Power","x",2]]],["Power",["Add","a",["Multiply","b",["Power","x",2]],["Multiply","c",["Power","x",4]]],["Subtract","p",1]]],"x"]]],"condition":["And",["FreeQ",["List","a","b","c","d","m"],"x"],["NeQ",["Subtract",["Power","b",2],["Multiply",4,"a","c"]],0],["GtQ","p",0],["NeQ",["Add","m",["Multiply",4,"p"],1],0],["IntegerQ",["Multiply",2,"p"]],["Or",["IntegerQ","p"],["IntegerQ","m"]]],"bindings":[],"scoped":null,"innerCondition":null,"source":"Int[(d_.*x_)^m_*(a_+b_.*x_^2+c_.*x_^4)^p_,x_Symbol] :=\r\n  (d*x)^(m+1)*(a+b*x^2+c*x^4)^p/(d*(m+4*p+1)) + \r\n  2*p/(m+4*p+1) \\[Star] Int[(d*x)^m*(2*a+b*x^2)*(a+b*x^2+c*x^4)^(p-1),x] /;\r\nFreeQ[{a,b,c,d,m},x] && NeQ[b^2-4*a*c,0] && GtQ[p,0] && NeQ[m+4*p+1,0] && IntegerQ[2*p] && (IntegerQ[p] || IntegerQ[m])"},
{"index":21,"lhs":["Multiply",["Power",["Multiply",["BlankOptional","d"],["Blank","x"]],["Blank","m"]],["Power",["Add",["Blank","a"],["Multiply",["BlankOptional","b"],["Power",["Blank","x"],2]],["Multiply",["BlankOptional","c"],["Power",["Blank","x"],4]]],["Blank","p"]]],"variable":"x","rhs":["Subtract",["Divide",["Multiply","d",["Power",["Multiply","d","x"],["Subtract","m",1]],["Add","b",["Multiply",2,"c",["Power","x",2]]],["Power",["Add","a",["Multiply","b",["Power","x",2]],["Multiply","c",["Power","x",4]]],["Add","p",1]]],["Multiply",2,["Add","p",1],["Subtract",["Power","b",2],["Multiply",4,"a","c"]]]],["Multiply",["Divide",["Power","d",2],["Multiply",2,["Add","p",1],["Subtract",["Power","b",2],["Multiply",4,"a","c"]]]],["Int",["Multiply",["Power",["Multiply","d","x"],["Subtract","m",2]],["Add",["Multiply","b",["Subtract","m",1]],["Multiply",2,"c",["Add","m",["Multiply",4,"p"],5],["Power","x",2]]],["Power",["Add","a",["Multiply","b",["Power","x",2]],["Multiply","c",["Power","x",4]]],["Add","p",1]]],"x"]]],"condition":["And",["FreeQ",["List","a","b","c","d"],"x"],["NeQ",["Subtract",["Power","b",2],["Multiply",4,"a","c"]],0],["LtQ","p",-1],["GtQ","m",1],["LeQ","m",3],["IntegerQ",["Multiply",2,"p"]],["Or",["IntegerQ","p"],["IntegerQ","m"]]],"bindings":[],"scoped":null,"innerCondition":null,"source":"Int[(d_.*x_)^m_*(a_+b_.*x_^2+c_.*x_^4)^p_,x_Symbol] :=\r\n  d*(d*x)^(m-1)*(b+2*c*x^2)*(a+b*x^2+c*x^4)^(p+1)/(2*(p+1)*(b^2-4*a*c)) - \r\n  d^2/(2*(p+1)*(b^2-4*a*c)) \\[Star] Int[(d*x)^(m-2)*(b*(m-1)+2*c*(m+4*p+5)*x^2)*(a+b*x^2+c*x^4)^(p+1),x] /;\r\nFreeQ[{a,b,c,d},x] && NeQ[b^2-4*a*c,0] && LtQ[p,-1] && GtQ[m,1] && LeQ[m,3] && IntegerQ[2*p] && (IntegerQ[p] || IntegerQ[m])"},
{"index":22,"lhs":["Multiply",["Power",["Multiply",["BlankOptional","d"],["Blank","x"]],["Blank","m"]],["Power",["Add",["Blank","a"],["Multiply",["BlankOptional","b"],["Power",["Blank","x"],2]],["Multiply",["BlankOptional","c"],["Power",["Blank","x"],4]]],["Blank","p"]]],"variable":"x","rhs":["Add",["Negate",["Divide",["Multiply",["Power","d",3],["Power",["Multiply","d","x"],["Subtract","m",3]],["Add",["Multiply",2,"a"],["Multiply","b",["Power","x",2]]],["Power",["Add","a",["Multiply","b",["Power","x",2]],["Multiply","c",["Power","x",4]]],["Add","p",1]]],["Multiply",2,["Add","p",1],["Subtract",["Power","b",2],["Multiply",4,"a","c"]]]]],["Multiply",["Divide",["Power","d",4],["Multiply",2,["Add","p",1],["Subtract",["Power","b",2],["Multiply",4,"a","c"]]]],["Int",["Multiply",["Power",["Multiply","d","x"],["Subtract","m",4]],["Add",["Multiply",2,"a",["Subtract","m",3]],["Multiply","b",["Add","m",["Multiply",4,"p"],3],["Power","x",2]]],["Power",["Add","a",["Multiply","b",["Power","x",2]],["Multiply","c",["Power","x",4]]],["Add","p",1]]],"x"]]],"condition":["And",["FreeQ",["List","a","b","c","d"],"x"],["NeQ",["Subtract",["Power","b",2],["Multiply",4,"a","c"]],0],["LtQ","p",-1],["GtQ","m",3],["IntegerQ",["Multiply",2,"p"]],["Or",["IntegerQ","p"],["IntegerQ","m"]]],"bindings":[],"scoped":null,"innerCondition":null,"source":"Int[(d_.*x_)^m_*(a_+b_.*x_^2+c_.*x_^4)^p_,x_Symbol] :=\r\n  -d^3*(d*x)^(m-3)*(2*a+b*x^2)*(a+b*x^2+c*x^4)^(p+1)/(2*(p+1)*(b^2-4*a*c)) + \r\n  d^4/(2*(p+1)*(b^2-4*a*c)) \\[Star] Int[(d*x)^(m-4)*(2*a*(m-3)+b*(m+4*p+3)*x^2)*(a+b*x^2+c*x^4)^(p+1),x] /;\r\nFreeQ[{a,b,c,d},x] && NeQ[b^2-4*a*c,0] && LtQ[p,-1] && GtQ[m,3] && IntegerQ[2*p] && (IntegerQ[p] || IntegerQ[m])"},
{"index":23,"lhs":["Multiply",["Power",["Multiply",["BlankOptional","d"],["Blank","x"]],["Blank","m"]],["Power",["Add",["Blank","a"],["Multiply",["BlankOptional","b"],["Power",["Blank","x"],2]],["Multiply",["BlankOptional","c"],["Power",["Blank","x"],4]]],["Blank","p"]]],"variable":"x","rhs":["Add",["Negate",["Divide",["Multiply",["Power",["Multiply","d","x"],["Add","m",1]],["Add",["Subtract",["Power","b",2],["Multiply",2,"a","c"]],["Multiply","b","c",["Power","x",2]]],["Power",["Add","a",["Multiply","b",["Power","x",2]],["Multiply","c",["Power","x",4]]],["Add","p",1]]],["Multiply",2,"a","d",["Add","p",1],["Subtract",["Power","b",2],["Multiply",4,"a","c"]]]]],["Multiply",["Divide",1,["Multiply",2,"a",["Add","p",1],["Subtract",["Power","b",2],["Multiply",4,"a","c"]]]],["Int",["Multiply",["Power",["Multiply","d","x"],"m"],["Power",["Add","a",["Multiply","b",["Power","x",2]],["Multiply","c",["Power","x",4]]],["Add","p",1]],["Simp",["Add",["Subtract",["Multiply",["Power","b",2],["Add","m",["Multiply",2,"p"],3]],["Multiply",2,"a","c",["Add","m",["Multiply",4,"p"],5]]],["Multiply","b","c",["Add","m",["Multiply",4,"p"],7],["Power","x",2]]],"x"]],"x"]]],"condition":["And",["FreeQ",["List","a","b","c","d","m"],"x"],["NeQ",["Subtract",["Power","b",2],["Multiply",4,"a","c"]],0],["LtQ","p",-1],["IntegerQ",["Multiply",2,"p"]],["Or",["IntegerQ","p"],["IntegerQ","m"]]],"bindings":[],"scoped":null,"innerCondition":null,"source":"Int[(d_.*x_)^m_*(a_+b_.*x_^2+c_.*x_^4)^p_,x_Symbol] :=\r\n  -(d*x)^(m+1)*(b^2-2*a*c+b*c*x^2)*(a+b*x^2+c*x^4)^(p+1)/(2*a*d*(p+1)*(b^2-4*a*c)) + \r\n  1/(2*a*(p+1)*(b^2-4*a*c)) \\[Star] \r\n    Int[(d*x)^m*(a+b*x^2+c*x^4)^(p+1)*Simp[b^2*(m+2*p+3)-2*a*c*(m+4*p+5)+b*c*(m+4*p+7)*x^2,x],x] /;\r\nFreeQ[{a,b,c,d,m},x] && NeQ[b^2-4*a*c,0] && LtQ[p,-1] && IntegerQ[2*p] && (IntegerQ[p] || IntegerQ[m])"},
{"index":24,"lhs":["Multiply",["Power",["Multiply",["BlankOptional","d"],["Blank","x"]],["Blank","m"]],["Power",["Add",["Blank","a"],["Multiply",["BlankOptional","b"],["Power",["Blank","x"],2]],["Multiply",["BlankOptional","c"],["Power",["Blank","x"],4]]],["Blank","p"]]],"variable":"x","rhs":["Subtract",["Divide",["Multiply",["Power","d",3],["Power",["Multiply","d","x"],["Subtract","m",3]],["Power",["Add","a",["Multiply","b",["Power","x",2]],["Multiply","c",["Power","x",4]]],["Add","p",1]]],["Multiply","c",["Add","m",["Multiply",4,"p"],1]]],["Multiply",["Divide",["Power","d",4],["Multiply","c",["Add","m",["Multiply",4,"p"],1]]],["Int",["Multiply",["Power",["Multiply","d","x"],["Subtract","m",4]],["Simp",["Add",["Multiply","a",["Subtract","m",3]],["Multiply","b",["Subtract",["Add","m",["Multiply",2,"p"]],1],["Power","x",2]]],"x"],["Power",["Add","a",["Multiply","b",["Power","x",2]],["Multiply","c",["Power","x",4]]],"p"]],"x"]]],"condition":["And",["FreeQ",["List","a","b","c","d","p"],"x"],["NeQ",["Subtract",["Power","b",2],["Multiply",4,"a","c"]],0],["GtQ","m",3],["NeQ",["Add","m",["Multiply",4,"p"],1],0],["IntegerQ",["Multiply",2,"p"]],["Or",["IntegerQ","p"],["IntegerQ","m"]]],"bindings":[],"scoped":null,"innerCondition":null,"source":"Int[(d_.*x_)^m_*(a_+b_.*x_^2+c_.*x_^4)^p_,x_Symbol] :=\r\n  d^3*(d*x)^(m-3)*(a+b*x^2+c*x^4)^(p+1)/(c*(m+4*p+1)) - \r\n  d^4/(c*(m+4*p+1)) \\[Star] \r\n    Int[(d*x)^(m-4)*Simp[a*(m-3)+b*(m+2*p-1)*x^2,x]*(a+b*x^2+c*x^4)^p,x] /;\r\nFreeQ[{a,b,c,d,p},x] && NeQ[b^2-4*a*c,0] && GtQ[m,3] && NeQ[m+4*p+1,0] && IntegerQ[2*p] && (IntegerQ[p] || IntegerQ[m])"},
{"index":25,"lhs":["Multiply",["Power",["Multiply",["BlankOptional","d"],["Blank","x"]],["Blank","m"]],["Power",["Add",["Blank","a"],["Multiply",["BlankOptional","b"],["Power",["Blank","x"],2]],["Multiply",["BlankOptional","c"],["Power",["Blank","x"],4]]],["Blank","p"]]],"variable":"x","rhs":["Subtract",["Divide",["Multiply",["Power",["Multiply","d","x"],["Add","m",1]],["Power",["Add","a",["Multiply","b",["Power","x",2]],["Multiply","c",["Power","x",4]]],["Add","p",1]]],["Multiply","a","d",["Add","m",1]]],["Multiply",["Divide",1,["Multiply","a",["Power","d",2],["Add","m",1]]],["Int",["Multiply",["Power",["Multiply","d","x"],["Add","m",2]],["Add",["Multiply","b",["Add","m",["Multiply",2,"p"],3]],["Multiply","c",["Add","m",["Multiply",4,"p"],5],["Power","x",2]]],["Power",["Add","a",["Multiply","b",["Power","x",2]],["Multiply","c",["Power","x",4]]],"p"]],"x"]]],"condition":["And",["FreeQ",["List","a","b","c","d","p"],"x"],["NeQ",["Subtract",["Power","b",2],["Multiply",4,"a","c"]],0],["LtQ","m",-1],["IntegerQ",["Multiply",2,"p"]],["Or",["IntegerQ","p"],["IntegerQ","m"]]],"bindings":[],"scoped":null,"innerCondition":null,"source":"Int[(d_.*x_)^m_*(a_+b_.*x_^2+c_.*x_^4)^p_,x_Symbol] :=\r\n  (d*x)^(m+1)*(a+b*x^2+c*x^4)^(p+1)/(a*d*(m+1)) - \r\n  1/(a*d^2*(m+1)) \\[Star] Int[(d*x)^(m+2)*(b*(m+2*p+3)+c*(m+4*p+5)*x^2)*(a+b*x^2+c*x^4)^p,x] /;\r\nFreeQ[{a,b,c,d,p},x] && NeQ[b^2-4*a*c,0] && LtQ[m,-1] && IntegerQ[2*p] && (IntegerQ[p] || IntegerQ[m])"},
{"index":26,"lhs":["Divide",["Power",["Multiply",["BlankOptional","d"],["Blank","x"]],["Blank","m"]],["Add",["Blank","a"],["Multiply",["BlankOptional","b"],["Power",["Blank","x"],2]],["Multiply",["BlankOptional","c"],["Power",["Blank","x"],4]]]],"variable":"x","rhs":["Subtract",["Divide",["Power",["Multiply","d","x"],["Add","m",1]],["Multiply","a","d",["Add","m",1]]],["Multiply",["Divide",1,["Multiply","a",["Power","d",2]]],["Int",["Divide",["Multiply",["Power",["Multiply","d","x"],["Add","m",2]],["Add","b",["Multiply","c",["Power","x",2]]]],["Add","a",["Multiply","b",["Power","x",2]],["Multiply","c",["Power","x",4]]]],"x"]]],"condition":["And",["FreeQ",["List","a","b","c","d"],"x"],["NeQ",["Subtract",["Power","b",2],["Multiply",4,"a","c"]],0],["LtQ","m",-1]],"bindings":[],"scoped":null,"innerCondition":null,"source":"Int[(d_.*x_)^m_/(a_+b_.*x_^2+c_.*x_^4),x_Symbol] :=\r\n  (d*x)^(m+1)/(a*d*(m+1)) -\r\n  1/(a*d^2) \\[Star] Int[(d*x)^(m+2)*(b+c*x^2)/(a+b*x^2+c*x^4),x] /;\r\nFreeQ[{a,b,c,d},x] && NeQ[b^2-4*a*c,0] && LtQ[m,-1]"},
{"index":27,"lhs":["Divide",["Power",["Blank","x"],["Blank","m"]],["Add",["Blank","a"],["Multiply",["BlankOptional","b"],["Power",["Blank","x"],2]],["Multiply",["BlankOptional","c"],["Power",["Blank","x"],4]]]],"variable":"x","rhs":["Int",["PolynomialDivide",["Power","x","m"],["Add","a",["Multiply","b",["Power","x",2]],["Multiply","c",["Power","x",4]]],"x"],"x"],"condition":["And",["FreeQ",["List","a","b","c"],"x"],["NeQ",["Subtract",["Power","b",2],["Multiply",4,"a","c"]],0],["IGtQ","m",5]],"bindings":[],"scoped":null,"innerCondition":null,"source":"Int[x_^m_/(a_+b_.*x_^2+c_.*x_^4),x_Symbol] :=\r\n  Int[PolynomialDivide[x^m,(a+b*x^2+c*x^4),x],x] /;\r\nFreeQ[{a,b,c},x] && NeQ[b^2-4*a*c,0] && IGtQ[m,5]"},
{"index":28,"lhs":["Divide",["Power",["Multiply",["BlankOptional","d"],["Blank","x"]],["Blank","m"]],["Add",["Blank","a"],["Multiply",["BlankOptional","b"],["Power",["Blank","x"],2]],["Multiply",["BlankOptional","c"],["Power",["Blank","x"],4]]]],"variable":"x","rhs":["Subtract",["Divide",["Multiply",["Power","d",3],["Power",["Multiply","d","x"],["Subtract","m",3]]],["Multiply","c",["Subtract","m",3]]],["Multiply",["Divide",["Power","d",4],"c"],["Int",["Divide",["Multiply",["Power",["Multiply","d","x"],["Subtract","m",4]],["Add","a",["Multiply","b",["Power","x",2]]]],["Add","a",["Multiply","b",["Power","x",2]],["Multiply","c",["Power","x",4]]]],"x"]]],"condition":["And",["FreeQ",["List","a","b","c","d"],"x"],["NeQ",["Subtract",["Power","b",2],["Multiply",4,"a","c"]],0],["GtQ","m",3]],"bindings":[],"scoped":null,"innerCondition":null,"source":"Int[(d_.*x_)^m_/(a_+b_.*x_^2+c_.*x_^4),x_Symbol] :=\r\n  d^3*(d*x)^(m-3)/(c*(m-3)) - d^4/c \\[Star] Int[(d*x)^(m-4)*(a+b*x^2)/(a+b*x^2+c*x^4),x] /;\r\nFreeQ[{a,b,c,d},x] && NeQ[b^2-4*a*c,0] && GtQ[m,3]"},
{"index":29,"lhs":["Divide",["Power",["Blank","x"],2],["Add",["Blank","a"],["Multiply",["BlankOptional","b"],["Power",["Blank","x"],2]],["Multiply",["BlankOptional","c"],["Power",["Blank","x"],4]]]],"variable":"x","rhs":["Subtract",["Multiply",["Rational",1,2],["Int",["Divide",["Add","q",["Power","x",2]],["Add","a",["Multiply","b",["Power","x",2]],["Multiply","c",["Power","x",4]]]],"x"]],["Multiply",["Rational",1,2],["Int",["Divide",["Subtract","q",["Power","x",2]],["Add","a",["Multiply","b",["Power","x",2]],["Multiply","c",["Power","x",4]]]],"x"]]],"condition":["And",["FreeQ",["List","a","b","c"],"x"],["LtQ",["Subtract",["Power","b",2],["Multiply",4,"a","c"]],0],["PosQ",["Multiply","a","c"]]],"bindings":[{"name":"q","value":["Rt",["Divide","a","c"],2]}],"scoped":"with","innerCondition":null,"source":"Int[x_^2/(a_+b_.*x_^2+c_.*x_^4), x_Symbol] :=\r\n  With[{q=Rt[a/c,2]},\r\n  1/2 \\[Star] Int[(q+x^2)/(a+b*x^2+c*x^4),x] - 1/2 \\[Star] Int[(q-x^2)/(a+b*x^2+c*x^4),x]] /;\r\nFreeQ[{a,b,c},x] && LtQ[b^2-4*a*c,0] && PosQ[a*c]"},
{"index":30,"lhs":["Divide",["Power",["Blank","x"],["Blank","m"]],["Add",["Blank","a"],["Multiply",["BlankOptional","b"],["Power",["Blank","x"],2]],["Multiply",["BlankOptional","c"],["Power",["Blank","x"],4]]]],"variable":"x","rhs":["Subtract",["Multiply",["Divide",1,["Multiply",2,"c","r"]],["Int",["Divide",["Multiply",["Power","x",["Subtract","m",3]],["Add","q",["Multiply","r","x"]]],["Add","q",["Multiply","r","x"],["Power","x",2]]],"x"]],["Multiply",["Divide",1,["Multiply",2,"c","r"]],["Int",["Divide",["Multiply",["Power","x",["Subtract","m",3]],["Subtract","q",["Multiply","r","x"]]],["Add",["Subtract","q",["Multiply","r","x"]],["Power","x",2]]],"x"]]],"condition":["And",["FreeQ",["List","a","b","c"],"x"],["NeQ",["Subtract",["Power","b",2],["Multiply",4,"a","c"]],0],["GeQ","m",3],["LtQ","m",4],["NegQ",["Subtract",["Power","b",2],["Multiply",4,"a","c"]]]],"bindings":[{"name":"q","value":["Rt",["Divide","a","c"],2]},{"name":"r","value":["Rt",["Subtract",["Multiply",2,"q"],["Divide","b","c"]],2]}],"scoped":"with","innerCondition":null,"source":"Int[x_^m_/(a_+b_.*x_^2+c_.*x_^4),x_Symbol] :=\r\n  With[{q=Rt[a/c,2]},\r\n  With[{r=Rt[2*q-b/c,2]},\r\n  1/(2*c*r) \\[Star] Int[x^(m-3)*(q+r*x)/(q+r*x+x^2),x] - \r\n  1/(2*c*r) \\[Star] Int[x^(m-3)*(q-r*x)/(q-r*x+x^2),x]]] /;\r\nFreeQ[{a,b,c},x] && NeQ[b^2-4*a*c,0] && GeQ[m,3] && LtQ[m,4] && NegQ[b^2-4*a*c]"},
{"index":31,"lhs":["Divide",["Power",["Blank","x"],["Blank","m"]],["Add",["Blank","a"],["Multiply",["BlankOptional","b"],["Power",["Blank","x"],2]],["Multiply",["BlankOptional","c"],["Power",["Blank","x"],4]]]],"variable":"x","rhs":["Subtract",["Multiply",["Divide",1,["Multiply",2,"c","r"]],["Int",["Divide",["Power","x",["Subtract","m",1]],["Add",["Subtract","q",["Multiply","r","x"]],["Power","x",2]]],"x"]],["Multiply",["Divide",1,["Multiply",2,"c","r"]],["Int",["Divide",["Power","x",["Subtract","m",1]],["Add","q",["Multiply","r","x"],["Power","x",2]]],"x"]]],"condition":["And",["FreeQ",["List","a","b","c"],"x"],["NeQ",["Subtract",["Power","b",2],["Multiply",4,"a","c"]],0],["GeQ","m",1],["LtQ","m",3],["NegQ",["Subtract",["Power","b",2],["Multiply",4,"a","c"]]]],"bindings":[{"name":"q","value":["Rt",["Divide","a","c"],2]},{"name":"r","value":["Rt",["Subtract",["Multiply",2,"q"],["Divide","b","c"]],2]}],"scoped":"with","innerCondition":null,"source":"Int[x_^m_/(a_+b_.*x_^2+c_.*x_^4),x_Symbol] :=\r\n  With[{q=Rt[a/c,2]},\r\n  With[{r=Rt[2*q-b/c,2]},\r\n  1/(2*c*r) \\[Star] Int[x^(m-1)/(q-r*x+x^2),x] - 1/(2*c*r) \\[Star] Int[x^(m-1)/(q+r*x+x^2),x]]] /;\r\nFreeQ[{a,b,c},x] && NeQ[b^2-4*a*c,0] && GeQ[m,1] && LtQ[m,3] && NegQ[b^2-4*a*c]"},
{"index":32,"lhs":["Divide",["Power",["Multiply",["BlankOptional","d"],["Blank","x"]],["Blank","m"]],["Add",["Blank","a"],["Multiply",["BlankOptional","b"],["Power",["Blank","x"],2]],["Multiply",["BlankOptional","c"],["Power",["Blank","x"],4]]]],"variable":"x","rhs":["Subtract",["Multiply",["Divide",["Power","d",2],2],["Add",["Divide","b","q"],1],["Int",["Divide",["Power",["Multiply","d","x"],["Subtract","m",2]],["Add",["Divide","b",2],["Divide","q",2],["Multiply","c",["Power","x",2]]]],"x"]],["Multiply",["Divide",["Power","d",2],2],["Subtract",["Divide","b","q"],1],["Int",["Divide",["Power",["Multiply","d","x"],["Subtract","m",2]],["Add",["Subtract",["Divide","b",2],["Divide","q",2]],["Multiply","c",["Power","x",2]]]],"x"]]],"condition":["And",["FreeQ",["List","a","b","c","d"],"x"],["NeQ",["Subtract",["Power","b",2],["Multiply",4,"a","c"]],0],["GeQ","m",2]],"bindings":[{"name":"q","value":["Rt",["Subtract",["Power","b",2],["Multiply",4,"a","c"]],2]}],"scoped":"with","innerCondition":null,"source":"Int[(d_.*x_)^m_/(a_+b_.*x_^2+c_.*x_^4),x_Symbol] :=\r\n  With[{q=Rt[b^2-4*a*c,2]},\r\n  d^2/2*(b/q+1) \\[Star] Int[(d*x)^(m-2)/(b/2+q/2+c*x^2),x] - \r\n  d^2/2*(b/q-1) \\[Star] Int[(d*x)^(m-2)/(b/2-q/2+c*x^2),x]] /;\r\nFreeQ[{a,b,c,d},x] && NeQ[b^2-4*a*c,0] && GeQ[m,2]"},
{"index":33,"lhs":["Divide",["Power",["Multiply",["BlankOptional","d"],["Blank","x"]],["Blank","m"]],["Add",["Blank","a"],["Multiply",["BlankOptional","b"],["Power",["Blank","x"],2]],["Multiply",["BlankOptional","c"],["Power",["Blank","x"],4]]]],"variable":"x","rhs":["Subtract",["Multiply",["Divide","c","q"],["Int",["Divide",["Power",["Multiply","d","x"],"m"],["Add",["Subtract",["Divide","b",2],["Divide","q",2]],["Multiply","c",["Power","x",2]]]],"x"]],["Multiply",["Divide","c","q"],["Int",["Divide",["Power",["Multiply","d","x"],"m"],["Add",["Divide","b",2],["Divide","q",2],["Multiply","c",["Power","x",2]]]],"x"]]],"condition":["And",["FreeQ",["List","a","b","c","d","m"],"x"],["NeQ",["Subtract",["Power","b",2],["Multiply",4,"a","c"]],0]],"bindings":[{"name":"q","value":["Rt",["Subtract",["Power","b",2],["Multiply",4,"a","c"]],2]}],"scoped":"with","innerCondition":null,"source":"Int[(d_.*x_)^m_/(a_+b_.*x_^2+c_.*x_^4),x_Symbol] :=\r\n  With[{q=Rt[b^2-4*a*c,2]},\r\n  c/q \\[Star] Int[(d*x)^m/(b/2-q/2+c*x^2),x] - c/q \\[Star] Int[(d*x)^m/(b/2+q/2+c*x^2),x]] /;\r\nFreeQ[{a,b,c,d,m},x] && NeQ[b^2-4*a*c,0]"},
{"index":34,"lhs":["Divide",["Power",["Blank","x"],2],["Sqrt",["Add",["Blank","a"],["Multiply",["BlankOptional","b"],["Power",["Blank","x"],2]],["Multiply",["BlankOptional","c"],["Power",["Blank","x"],4]]]]],"variable":"x","rhs":["Multiply",2,["Sqrt",["Negate","c"]],["Int",["Divide",["Power","x",2],["Multiply",["Sqrt",["Add","b","q",["Multiply",2,"c",["Power","x",2]]]],["Sqrt",["Subtract",["Add",["Negate","b"],"q"],["Multiply",2,"c",["Power","x",2]]]]]],"x"]],"condition":["And",["FreeQ",["List","a","b","c"],"x"],["GtQ",["Subtract",["Power","b",2],["Multiply",4,"a","c"]],0],["LtQ","c",0]],"bindings":[{"name":"q","value":["Rt",["Subtract",["Power","b",2],["Multiply",4,"a","c"]],2]}],"scoped":"with","innerCondition":null,"source":"Int[x_^2/Sqrt[a_+b_.*x_^2+c_.*x_^4],x_Symbol] :=\r\n  With[{q=Rt[b^2-4*a*c,2]},\r\n  2*Sqrt[-c] \\[Star] Int[x^2/(Sqrt[b+q+2*c*x^2]*Sqrt[-b+q-2*c*x^2]),x]] /;\r\nFreeQ[{a,b,c},x] && GtQ[b^2-4*a*c,0] && LtQ[c,0]"},
{"index":35,"lhs":["Divide",["Power",["Blank","x"],2],["Sqrt",["Add",["Blank","a"],["Multiply",["BlankOptional","b"],["Power",["Blank","x"],2]],["Multiply",["BlankOptional","c"],["Power",["Blank","x"],4]]]]],"variable":"x","rhs":["Subtract",["Multiply",["Divide",1,"q"],["Int",["Divide",1,["Sqrt",["Add","a",["Multiply","b",["Power","x",2]],["Multiply","c",["Power","x",4]]]]],"x"]],["Multiply",["Divide",1,"q"],["Int",["Divide",["Subtract",1,["Multiply","q",["Power","x",2]]],["Sqrt",["Add","a",["Multiply","b",["Power","x",2]],["Multiply","c",["Power","x",4]]]]],"x"]]],"condition":["And",["FreeQ",["List","a","b","c"],"x"],["GtQ",["Subtract",["Power","b",2],["Multiply",4,"a","c"]],0],["GtQ",["Divide","c","a"],0],["LtQ",["Divide","b","a"],0]],"bindings":[{"name":"q","value":["Rt",["Divide","c","a"],2]}],"scoped":"with","innerCondition":null,"source":"Int[x_^2/Sqrt[a_+b_.*x_^2+c_.*x_^4],x_Symbol] :=\r\n  With[{q=Rt[c/a,2]},\r\n  1/q \\[Star] Int[1/Sqrt[a+b*x^2+c*x^4],x] - 1/q \\[Star] Int[(1-q*x^2)/Sqrt[a+b*x^2+c*x^4],x]] /;\r\nFreeQ[{a,b,c},x] && GtQ[b^2-4*a*c,0] && GtQ[c/a,0] && LtQ[b/a,0]"},
{"index":36,"lhs":["Divide",["Power",["Blank","x"],2],["Sqrt",["Add",["Blank","a"],["Multiply",["BlankOptional","b"],["Power",["Blank","x"],2]],["Multiply",["BlankOptional","c"],["Power",["Blank","x"],4]]]]],"variable":"x","rhs":["Add",["Negate",["Multiply",["Divide",["Subtract","b","q"],["Multiply",2,"c"]],["Int",["Divide",1,["Sqrt",["Add","a",["Multiply","b",["Power","x",2]],["Multiply","c",["Power","x",4]]]]],"x"]]],["Multiply",["Divide",1,["Multiply",2,"c"]],["Int",["Divide",["Add",["Subtract","b","q"],["Multiply",2,"c",["Power","x",2]]],["Sqrt",["Add","a",["Multiply","b",["Power","x",2]],["Multiply","c",["Power","x",4]]]]],"x"]]],"condition":["And",["FreeQ",["List","a","b","c"],"x"],["GtQ",["Subtract",["Power","b",2],["Multiply",4,"a","c"]],0],["LtQ","a",0],["GtQ","c",0]],"bindings":[{"name":"q","value":["Rt",["Subtract",["Power","b",2],["Multiply",4,"a","c"]],2]}],"scoped":"with","innerCondition":null,"source":"Int[x_^2/Sqrt[a_+b_.*x_^2+c_.*x_^4],x_Symbol] :=\r\n  With[{q=Rt[b^2-4*a*c,2]},\r\n  -(b-q)/(2*c) \\[Star] Int[1/Sqrt[a+b*x^2+c*x^4],x] + 1/(2*c) \\[Star] Int[(b-q+2*c*x^2)/Sqrt[a+b*x^2+c*x^4],x]] /;\r\nFreeQ[{a,b,c},x] && GtQ[b^2-4*a*c,0] && LtQ[a,0] && GtQ[c,0]"},
{"index":37,"lhs":["Divide",["Power",["Blank","x"],2],["Sqrt",["Add",["Blank","a"],["Multiply",["BlankOptional","b"],["Power",["Blank","x"],2]],["Multiply",["BlankOptional","c"],["Power",["Blank","x"],4]]]]],"variable":"x","rhs":["Subtract",["Divide",["Multiply","x",["Add","b","q",["Multiply",2,"c",["Power","x",2]]]],["Multiply",2,"c",["Sqrt",["Add","a",["Multiply","b",["Power","x",2]],["Multiply","c",["Power","x",4]]]]]],["Multiply",["Divide",["Multiply",["Rt",["Divide",["Add","b","q"],["Multiply",2,"a"]],2],["Add",["Multiply",2,"a"],["Multiply",["Add","b","q"],["Power","x",2]]],["Sqrt",["Divide",["Add",["Multiply",2,"a"],["Multiply",["Subtract","b","q"],["Power","x",2]]],["Add",["Multiply",2,"a"],["Multiply",["Add","b","q"],["Power","x",2]]]]]],["Multiply",2,"c",["Sqrt",["Add","a",["Multiply","b",["Power","x",2]],["Multiply","c",["Power","x",4]]]]]],["EllipticE",["Arctan",["Multiply",["Rt",["Divide",["Add","b","q"],["Multiply",2,"a"]],2],"x"]],["Divide",["Multiply",2,"q"],["Add","b","q"]]]]],"condition":["And",["FreeQ",["List","a","b","c"],"x"],["GtQ",["Subtract",["Power","b",2],["Multiply",4,"a","c"]],0]],"bindings":[{"name":"q","value":["Rt",["Subtract",["Power","b",2],["Multiply",4,"a","c"]],2]}],"scoped":"with","innerCondition":["And",["PosQ",["Divide",["Add","b","q"],"a"]],["Not",["And",["PosQ",["Divide",["Subtract","b","q"],"a"]],["SimplerSqrtQ",["Divide",["Subtract","b","q"],["Multiply",2,"a"]],["Divide",["Add","b","q"],["Multiply",2,"a"]]]]]],"source":"Int[x_^2/Sqrt[a_+b_.*x_^2+c_.*x_^4],x_Symbol] :=\r\n  With[{q=Rt[b^2-4*a*c,2]},\r\n  x*(b+q+2*c*x^2)/(2*c*Sqrt[a+b*x^2+c*x^4]) - \r\n  Rt[(b+q)/(2*a),2]*(2*a+(b+q)*x^2)*Sqrt[(2*a+(b-q)*x^2)/(2*a+(b+q)*x^2)]/(2*c*Sqrt[a+b*x^2+c*x^4])*\r\n    EllipticE[ArcTan[Rt[(b+q)/(2*a),2]*x],2*q/(b+q)] /;\r\n PosQ[(b+q)/a] && Not[PosQ[(b-q)/a] && SimplerSqrtQ[(b-q)/(2*a),(b+q)/(2*a)]]] /;\r\nFreeQ[{a,b,c},x] && GtQ[b^2-4*a*c,0]"},
{"index":38,"lhs":["Divide",["Power",["Blank","x"],2],["Sqrt",["Add",["Blank","a"],["Multiply",["BlankOptional","b"],["Power",["Blank","x"],2]],["Multiply",["BlankOptional","c"],["Power",["Blank","x"],4]]]]],"variable":"x","rhs":["Subtract",["Divide",["Multiply","x",["Add",["Subtract","b","q"],["Multiply",2,"c",["Power","x",2]]]],["Multiply",2,"c",["Sqrt",["Add","a",["Multiply","b",["Power","x",2]],["Multiply","c",["Power","x",4]]]]]],["Multiply",["Divide",["Multiply",["Rt",["Divide",["Subtract","b","q"],["Multiply",2,"a"]],2],["Add",["Multiply",2,"a"],["Multiply",["Subtract","b","q"],["Power","x",2]]],["Sqrt",["Divide",["Add",["Multiply",2,"a"],["Multiply",["Add","b","q"],["Power","x",2]]],["Add",["Multiply",2,"a"],["Multiply",["Subtract","b","q"],["Power","x",2]]]]]],["Multiply",2,"c",["Sqrt",["Add","a",["Multiply","b",["Power","x",2]],["Multiply","c",["Power","x",4]]]]]],["EllipticE",["Arctan",["Multiply",["Rt",["Divide",["Subtract","b","q"],["Multiply",2,"a"]],2],"x"]],["Negate",["Divide",["Multiply",2,"q"],["Subtract","b","q"]]]]]],"condition":["And",["FreeQ",["List","a","b","c"],"x"],["GtQ",["Subtract",["Power","b",2],["Multiply",4,"a","c"]],0]],"bindings":[{"name":"q","value":["Rt",["Subtract",["Power","b",2],["Multiply",4,"a","c"]],2]}],"scoped":"with","innerCondition":["PosQ",["Divide",["Subtract","b","q"],"a"]],"source":"Int[x_^2/Sqrt[a_+b_.*x_^2+c_.*x_^4],x_Symbol] :=\r\n  With[{q=Rt[b^2-4*a*c,2]},\r\n  x*(b-q+2*c*x^2)/(2*c*Sqrt[a+b*x^2+c*x^4]) - \r\n  Rt[(b-q)/(2*a),2]*(2*a+(b-q)*x^2)*Sqrt[(2*a+(b+q)*x^2)/(2*a+(b-q)*x^2)]/(2*c*Sqrt[a+b*x^2+c*x^4])*\r\n    EllipticE[ArcTan[Rt[(b-q)/(2*a),2]*x],-2*q/(b-q)] /;\r\n PosQ[(b-q)/a]] /;\r\nFreeQ[{a,b,c},x] && GtQ[b^2-4*a*c,0]"},
{"index":39,"lhs":["Divide",["Power",["Blank","x"],2],["Sqrt",["Add",["Blank","a"],["Multiply",["BlankOptional","b"],["Power",["Blank","x"],2]],["Multiply",["BlankOptional","c"],["Power",["Blank","x"],4]]]]],"variable":"x","rhs":["Add",["Negate",["Multiply",["Divide",["Add","b","q"],["Multiply",2,"c"]],["Int",["Divide",1,["Sqrt",["Add","a",["Multiply","b",["Power","x",2]],["Multiply","c",["Power","x",4]]]]],"x"]]],["Multiply",["Divide",1,["Multiply",2,"c"]],["Int",["Divide",["Add","b","q",["Multiply",2,"c",["Power","x",2]]],["Sqrt",["Add","a",["Multiply","b",["Power","x",2]],["Multiply","c",["Power","x",4]]]]],"x"]]],"condition":["And",["FreeQ",["List","a","b","c"],"x"],["GtQ",["Subtract",["Power","b",2],["Multiply",4,"a","c"]],0]],"bindings":[{"name":"q","value":["Rt",["Subtract",["Power","b",2],["Multiply",4,"a","c"]],2]}],"scoped":"with","innerCondition":["And",["NegQ",["Divide",["Add","b","q"],"a"]],["Not",["And",["NegQ",["Divide",["Subtract","b","q"],"a"]],["SimplerSqrtQ",["Negate",["Divide",["Subtract","b","q"],["Multiply",2,"a"]]],["Negate",["Divide",["Add","b","q"],["Multiply",2,"a"]]]]]]],"source":"Int[x_^2/Sqrt[a_+b_.*x_^2+c_.*x_^4],x_Symbol] :=\r\n  With[{q=Rt[b^2-4*a*c,2]},\r\n  -(b+q)/(2*c) \\[Star] Int[1/Sqrt[a+b*x^2+c*x^4],x] + 1/(2*c) \\[Star] Int[(b+q+2*c*x^2)/Sqrt[a+b*x^2+c*x^4],x] /;\r\n NegQ[(b+q)/a] && Not[NegQ[(b-q)/a] && SimplerSqrtQ[-(b-q)/(2*a),-(b+q)/(2*a)]]] /;\r\nFreeQ[{a,b,c},x] && GtQ[b^2-4*a*c,0]"},
{"index":40,"lhs":["Divide",["Power",["Blank","x"],2],["Sqrt",["Add",["Blank","a"],["Multiply",["BlankOptional","b"],["Power",["Blank","x"],2]],["Multiply",["BlankOptional","c"],["Power",["Blank","x"],4]]]]],"variable":"x","rhs":["Add",["Negate",["Multiply",["Divide",["Subtract","b","q"],["Multiply",2,"c"]],["Int",["Divide",1,["Sqrt",["Add","a",["Multiply","b",["Power","x",2]],["Multiply","c",["Power","x",4]]]]],"x"]]],["Multiply",["Divide",1,["Multiply",2,"c"]],["Int",["Divide",["Add",["Subtract","b","q"],["Multiply",2,"c",["Power","x",2]]],["Sqrt",["Add","a",["Multiply","b",["Power","x",2]],["Multiply","c",["Power","x",4]]]]],"x"]]],"condition":["And",["FreeQ",["List","a","b","c"],"x"],["GtQ",["Subtract",["Power","b",2],["Multiply",4,"a","c"]],0]],"bindings":[{"name":"q","value":["Rt",["Subtract",["Power","b",2],["Multiply",4,"a","c"]],2]}],"scoped":"with","innerCondition":["NegQ",["Divide",["Subtract","b","q"],"a"]],"source":"Int[x_^2/Sqrt[a_+b_.*x_^2+c_.*x_^4],x_Symbol] :=\r\n  With[{q=Rt[b^2-4*a*c,2]},\r\n  -(b-q)/(2*c) \\[Star] Int[1/Sqrt[a+b*x^2+c*x^4],x] + 1/(2*c) \\[Star] Int[(b-q+2*c*x^2)/Sqrt[a+b*x^2+c*x^4],x] /;\r\n NegQ[(b-q)/a]] /;\r\nFreeQ[{a,b,c},x] && GtQ[b^2-4*a*c,0]"},
{"index":41,"lhs":["Divide",["Power",["Blank","x"],2],["Sqrt",["Add",["Blank","a"],["Multiply",["BlankOptional","b"],["Power",["Blank","x"],2]],["Multiply",["BlankOptional","c"],["Power",["Blank","x"],4]]]]],"variable":"x","rhs":["Subtract",["Multiply",["Divide",1,"q"],["Int",["Divide",1,["Sqrt",["Add","a",["Multiply","b",["Power","x",2]],["Multiply","c",["Power","x",4]]]]],"x"]],["Multiply",["Divide",1,"q"],["Int",["Divide",["Subtract",1,["Multiply","q",["Power","x",2]]],["Sqrt",["Add","a",["Multiply","b",["Power","x",2]],["Multiply","c",["Power","x",4]]]]],"x"]]],"condition":["And",["FreeQ",["List","a","b","c"],"x"],["NeQ",["Subtract",["Power","b",2],["Multiply",4,"a","c"]],0],["PosQ",["Divide","c","a"]]],"bindings":[{"name":"q","value":["Rt",["Divide","c","a"],2]}],"scoped":"with","innerCondition":null,"source":"Int[x_^2/Sqrt[a_+b_.*x_^2+c_.*x_^4],x_Symbol] :=\r\n  With[{q=Rt[c/a,2]},\r\n  1/q \\[Star] Int[1/Sqrt[a+b*x^2+c*x^4],x] - 1/q \\[Star] Int[(1-q*x^2)/Sqrt[a+b*x^2+c*x^4],x]] /;\r\nFreeQ[{a,b,c},x] && NeQ[b^2-4*a*c,0] && PosQ[c/a]"},
{"index":42,"lhs":["Divide",["Power",["Blank","x"],2],["Sqrt",["Add",["Blank","a"],["Multiply",["BlankOptional","b"],["Power",["Blank","x"],2]],["Multiply",["BlankOptional","c"],["Power",["Blank","x"],4]]]]],"variable":"x","rhs":["Multiply",["Divide",["Multiply",["Sqrt",["Add",1,["Divide",["Multiply",2,"c",["Power","x",2]],["Subtract","b","q"]]]],["Sqrt",["Add",1,["Divide",["Multiply",2,"c",["Power","x",2]],["Add","b","q"]]]]],["Sqrt",["Add","a",["Multiply","b",["Power","x",2]],["Multiply","c",["Power","x",4]]]]],["Int",["Divide",["Power","x",2],["Multiply",["Sqrt",["Add",1,["Divide",["Multiply",2,"c",["Power","x",2]],["Subtract","b","q"]]]],["Sqrt",["Add",1,["Divide",["Multiply",2,"c",["Power","x",2]],["Add","b","q"]]]]]],"x"]],"condition":["And",["FreeQ",["List","a","b","c"],"x"],["NeQ",["Subtract",["Power","b",2],["Multiply",4,"a","c"]],0],["NegQ",["Divide","c","a"]]],"bindings":[{"name":"q","value":["Rt",["Subtract",["Power","b",2],["Multiply",4,"a","c"]],2]}],"scoped":"with","innerCondition":null,"source":"Int[x_^2/Sqrt[a_+b_.*x_^2+c_.*x_^4],x_Symbol] :=\r\n  With[{q=Rt[b^2-4*a*c,2]},\r\n  Sqrt[1+2*c*x^2/(b-q)]*Sqrt[1+2*c*x^2/(b+q)]/Sqrt[a+b*x^2+c*x^4] \\[Star] \r\n    Int[x^2/(Sqrt[1+2*c*x^2/(b-q)]*Sqrt[1+2*c*x^2/(b+q)]),x]] /;\r\nFreeQ[{a,b,c},x] && NeQ[b^2-4*a*c,0] && NegQ[c/a]"},
{"index":43,"lhs":["Multiply",["Power",["Multiply",["BlankOptional","d"],["Blank","x"]],["Blank","m"]],["Power",["Add",["Blank","a"],["Multiply",["BlankOptional","b"],["Power",["Blank","x"],2]],["Multiply",["BlankOptional","c"],["Power",["Blank","x"],4]]],["Blank","p"]]],"variable":"x","rhs":["Multiply",["Divide",["Multiply",["Power","a",["IntPart","p"]],["Power",["Add","a",["Multiply","b",["Power","x",2]],["Multiply","c",["Power","x",4]]],["FracPart","p"]]],["Multiply",["Power",["Add",1,["Divide",["Multiply",2,"c",["Power","x",2]],["Add","b",["Rt",["Subtract",["Power","b",2],["Multiply",4,"a","c"]],2]]]],["FracPart","p"]],["Power",["Add",1,["Divide",["Multiply",2,"c",["Power","x",2]],["Subtract","b",["Rt",["Subtract",["Power","b",2],["Multiply",4,"a","c"]],2]]]],["FracPart","p"]]]],["Int",["Multiply",["Power",["Multiply","d","x"],"m"],["Power",["Add",1,["Divide",["Multiply",2,"c",["Power","x",2]],["Add","b",["Sqrt",["Subtract",["Power","b",2],["Multiply",4,"a","c"]]]]]],"p"],["Power",["Add",1,["Divide",["Multiply",2,"c",["Power","x",2]],["Subtract","b",["Sqrt",["Subtract",["Power","b",2],["Multiply",4,"a","c"]]]]]],"p"]],"x"]],"condition":["FreeQ",["List","a","b","c","d","m","p"],"x"],"bindings":[],"scoped":null,"innerCondition":null,"source":"Int[(d_.*x_)^m_*(a_+b_.*x_^2+c_.*x_^4)^p_,x_Symbol] :=\r\n  a^IntPart[p]*(a+b*x^2+c*x^4)^FracPart[p]/\r\n    ((1+2*c*x^2/(b+Rt[b^2-4*a*c,2]))^FracPart[p]*(1+2*c*x^2/(b-Rt[b^2-4*a*c,2]))^FracPart[p]) \\[Star] \r\n    Int[(d*x)^m*(1+2*c*x^2/(b+Sqrt[b^2-4*a*c]))^p*(1+2*c*x^2/(b-Sqrt[b^2-4*a*c]))^p,x] /;\r\nFreeQ[{a,b,c,d,m,p},x]"},
{"index":44,"lhs":["Multiply",["Power",["Blank","u"],["BlankOptional","m"]],["Power",["Add",["BlankOptional","a"],["Multiply",["BlankOptional","b"],["Power",["Blank","v"],2]],["Multiply",["BlankOptional","c"],["Power",["Blank","v"],4]]],["BlankOptional","p"]]],"variable":"x","rhs":["Multiply",["Divide",["Power","u","m"],["Multiply",["Coefficient","v","x",1],["Power","v","m"]]],["Subst",["Int",["Multiply",["Power","x","m"],["Power",["Add","a",["Multiply","b",["Power","x",2]],["Multiply","c",["Power","x",["Multiply",2,2]]]],"p"]],"x"],"x","v"]],"condition":["And",["FreeQ",["List","a","b","c","m","p"],"x"],["LinearPairQ","u","v","x"]],"bindings":[],"scoped":null,"innerCondition":null,"source":"Int[u_^m_.*(a_.+b_.*v_^2+c_.*v_^4)^p_.,x_Symbol] :=\r\n  u^m/(Coefficient[v,x,1]*v^m) \\[Star] Subst[Int[x^m*(a+b*x^2+c*x^(2*2))^p,x],x,v] /;\r\nFreeQ[{a,b,c,m,p},x] && LinearPairQ[u,v,x]"}
]}
